src/__init__.py
src/dc_cli.py
src/dc_utils.py
src/scripts/__init__.py
src/scripts/app-services/__init__.py
src/scripts/app-services/cluster-telemetry/Dockerfile
src/scripts/app-services/cluster-telemetry/clusterRole.yaml
src/scripts/app-services/cluster-telemetry/config-map.yaml
src/scripts/app-services/cluster-telemetry/grafana-dashboard.yaml
src/scripts/app-services/cluster-telemetry/grafana-datasource-config.yaml
src/scripts/app-services/cluster-telemetry/grafana-deployment.yaml
src/scripts/app-services/cluster-telemetry/grafana-login.yaml
src/scripts/app-services/cluster-telemetry/grafana-service.yaml
src/scripts/app-services/cluster-telemetry/kubernetes-dashboard.yaml
src/scripts/app-services/cluster-telemetry/prometheus-deployment.yaml
src/scripts/app-services/cluster-telemetry/prometheus-service.yaml
src/scripts/app-services/cluster-telemetry/start.sh
src/scripts/app-services/cluster-telemetry/stop.sh
src/scripts/app-services/docker-telemetry/__init__.py
src/scripts/app-services/docker-telemetry/docker-compose-app-service.yaml
src/scripts/app-services/docker-telemetry/start.sh
src/scripts/app-services/docker-telemetry/stop.sh
src/scripts/app-services/docker-telemetry/configs/__init__.py
src/scripts/app-services/docker-telemetry/configs/grafana.ini
src/scripts/app-services/docker-telemetry/configs/prometheus.yml
src/scripts/app-services/docker-telemetry/configs/grafana_dashboards/__init__.py
src/scripts/app-services/docker-telemetry/configs/grafana_dashboards/dashboard.yml
src/scripts/app-services/docker-telemetry/configs/grafana_dashboards/docker-container.json
src/scripts/app-services/docker-telemetry/configs/grafana_datasources/__init__.py
src/scripts/app-services/docker-telemetry/configs/grafana_datasources/prometheus-datasource.yml
src/scripts/app-services/health-check/__init__.py
src/scripts/app-services/health-check/docker-compose.yml
src/scripts/app-services/health-check/start.sh
src/scripts/app-services/health-check/stop.sh
devcloudcli-1.4.9.dist-info/LICENSE.txt
devcloudcli-1.4.9.dist-info/METADATA
devcloudcli-1.4.9.dist-info/WHEEL
devcloudcli-1.4.9.dist-info/entry_points.txt
devcloudcli-1.4.9.dist-info/top_level.txt
devcloudcli-1.4.9.dist-info/RECORD
